jupyterlab_nvidia_nsight/__init__.py
jupyterlab_nvidia_nsight/_version.py
jupyterlab_nvidia_nsight/handlers.py
jupyterlab_nvidia_nsight/nsight_tools.py
jupyterlab_nvidia_nsight/utils.py
jupyterlab_nvidia_nsight/webrtc_container.py
jupyterlab_nvidia_nsight/tests/__init__.py
jupyterlab_nvidia_nsight/tests/test_handlers.py
jupyterlab_nvidia_nsight-0.8.1.data/data/etc/jupyter/jupyter_server_config.d/jupyterlab_nvidia_nsight.json
jupyterlab_nvidia_nsight-0.8.1.data/data/share/jupyter/labextensions/jupyterlab-nvidia-nsight/package.json
jupyterlab_nvidia_nsight-0.8.1.data/data/share/jupyter/labextensions/jupyterlab-nvidia-nsight/schemas/jupyterlab-nvidia-nsight/package.json.orig
jupyterlab_nvidia_nsight-0.8.1.data/data/share/jupyter/labextensions/jupyterlab-nvidia-nsight/schemas/jupyterlab-nvidia-nsight/plugin.json
jupyterlab_nvidia_nsight-0.8.1.data/data/share/jupyter/labextensions/jupyterlab-nvidia-nsight/static/292.e0d62d32be793d521fe7.js
jupyterlab_nvidia_nsight-0.8.1.data/data/share/jupyter/labextensions/jupyterlab-nvidia-nsight/static/728.77e7287bdb023225d2cc.js
jupyterlab_nvidia_nsight-0.8.1.data/data/share/jupyter/labextensions/jupyterlab-nvidia-nsight/static/remoteEntry.22c432c5d246bbdeed21.js
jupyterlab_nvidia_nsight-0.8.1.data/data/share/jupyter/labextensions/jupyterlab-nvidia-nsight/static/style.js
jupyterlab_nvidia_nsight-0.8.1.data/data/share/jupyter/labextensions/jupyterlab-nvidia-nsight/static/third-party-licenses.json
jupyterlab_nvidia_nsight-0.8.1.data/data/share/jupyter/labextensions/jupyterlab-nvidia-nsight/install.json
jupyterlab_nvidia_nsight-0.8.1.dist-info/METADATA
jupyterlab_nvidia_nsight-0.8.1.dist-info/WHEEL
jupyterlab_nvidia_nsight-0.8.1.dist-info/licenses/License.txt
jupyterlab_nvidia_nsight-0.8.1.dist-info/RECORD
