Metadata-Version: 2.4
Name: jupyterlab_nvidia_nsight
Version: 0.8.1
Summary: A JupyterLab extension for profiling cells execution using NVIDIA Nsight tools.
Project-URL: Homepage, https://pypi.org/project/jupyterlab-nvidia-nsight
Project-URL: Bug Tracker, https://forums.developer.nvidia.com/c/developer-tools/nsight-systems/profiling-linux-targets
Author-email: NVIDIA Corporation <devtools-support@nvidia.com>
License: NVIDIA Proprietary Software
License-File: License.txt
Keywords: jupyter,jupyterlab,jupyterlab-extension
Classifier: Framework :: Jupyter
Classifier: Framework :: Jupyter :: JupyterLab
Classifier: Framework :: Jupyter :: JupyterLab :: 4
Classifier: Framework :: Jupyter :: JupyterLab :: Extensions
Classifier: Framework :: Jupyter :: JupyterLab :: Extensions :: Prebuilt
Classifier: License :: Other/Proprietary License
Classifier: Programming Language :: Python
Classifier: Programming Language :: Python :: 3
Classifier: Programming Language :: Python :: 3.9
Classifier: Programming Language :: Python :: 3.10
Classifier: Programming Language :: Python :: 3.11
Classifier: Programming Language :: Python :: 3.12
Classifier: Programming Language :: Python :: 3.13
Requires-Python: >=3.9
Requires-Dist: docker
Requires-Dist: jupyter-server<3,>=2.4.0
